researchmap/__init__.py
researchmap/adapter.py
researchmap/errors.py
researchmap/wrapper.py
researchmap.py-0.0.1.dist-info/AUTHORS
researchmap.py-0.0.1.dist-info/LICENSE
researchmap.py-0.0.1.dist-info/METADATA
researchmap.py-0.0.1.dist-info/WHEEL
researchmap.py-0.0.1.dist-info/top_level.txt
researchmap.py-0.0.1.dist-info/RECORD
