Metadata-Version: 2.1
Name: researchmap.py
Version: 0.0.1
Summary: This is a wrapper for the Researchmap API.
Home-page: https://github.com/RTa-technology/researchmap.py
Author: RTa-technology
License: MIT
Platform: UNKNOWN
Classifier: Programming Language :: Python :: 3.8
Classifier: Programming Language :: Python :: 3.9
Classifier: License :: OSI Approved :: MIT License
Classifier: Operating System :: OS Independent
License-File: LICENSE
License-File: AUTHORS
Requires-Dist: PyJWT
Requires-Dist: aiohttp
Requires-Dist: requestscryptography
Requires-Dist: sphinx
Requires-Dist: sphinxcontrib-trio
Requires-Dist: sphinxcontrib-websupport
Requires-Dist: myst-parser
Requires-Dist: urllib3
